thousandeyes_sdk/internet_insights/__init__.py
thousandeyes_sdk/internet_insights/py.typed
thousandeyes_sdk/internet_insights/api/__init__.py
thousandeyes_sdk/internet_insights/api/internet_insights_catalog_providers_api.py
thousandeyes_sdk/internet_insights/api/internet_insights_outages_api.py
thousandeyes_sdk/internet_insights/models/__init__.py
thousandeyes_sdk/internet_insights/models/api_application_outage_affected_location.py
thousandeyes_sdk/internet_insights/models/api_application_outage_affected_server.py
thousandeyes_sdk/internet_insights/models/api_application_outage_details.py
thousandeyes_sdk/internet_insights/models/api_asn.py
thousandeyes_sdk/internet_insights/models/api_catalog_provider.py
thousandeyes_sdk/internet_insights/models/api_catalog_provider_details.py
thousandeyes_sdk/internet_insights/models/api_catalog_provider_filter.py
thousandeyes_sdk/internet_insights/models/api_catalog_provider_response.py
thousandeyes_sdk/internet_insights/models/api_network_outage_affected_location.py
thousandeyes_sdk/internet_insights/models/api_network_outage_details.py
thousandeyes_sdk/internet_insights/models/api_outage.py
thousandeyes_sdk/internet_insights/models/api_outage_filter.py
thousandeyes_sdk/internet_insights/models/api_outages_response.py
thousandeyes_sdk/internet_insights/models/error.py
thousandeyes_sdk/internet_insights/models/internet_insights_api_affected_agent.py
thousandeyes_sdk/internet_insights/models/internet_insights_api_affected_test.py
thousandeyes_sdk/internet_insights/models/link.py
thousandeyes_sdk/internet_insights/models/outage_scope.py
thousandeyes_sdk/internet_insights/models/provider_location.py
thousandeyes_sdk/internet_insights/models/self_links.py
thousandeyes_sdk/internet_insights/models/unauthorized_error.py
thousandeyes_sdk/internet_insights/models/validation_error.py
thousandeyes_sdk/internet_insights/models/validation_error_item.py
thousandeyes_sdk_internet_insights-2.23.0.dist-info/licenses/LICENSE
thousandeyes_sdk_internet_insights-2.23.0.dist-info/licenses/NOTICE
thousandeyes_sdk_internet_insights-2.23.0.dist-info/METADATA
thousandeyes_sdk_internet_insights-2.23.0.dist-info/WHEEL
thousandeyes_sdk_internet_insights-2.23.0.dist-info/top_level.txt
thousandeyes_sdk_internet_insights-2.23.0.dist-info/RECORD
